{
  "F_infinity": 2.27,
  "threshold_fraction": 0.95,
  "threshold_F": 2.1565,
  "per_type": {
    "tool_state": {
      "usable_lifetime_days": 9.8,
      "F_at_day_0": 1.7685,
      "F_at_day_30": 2.3799,
      "F_at_day_100": 2.3783,
      "F_at_day_200": 2.3783,
      "reached_threshold": true
    },
    "episodic": {
      "usable_lifetime_days": 29.2,
      "F_at_day_0": 1.7685,
      "F_at_day_30": 2.1895,
      "F_at_day_100": 2.3792,
      "F_at_day_200": 2.3783,
      "reached_threshold": true
    },
    "semantic": {
      "usable_lifetime_days": 145.9,
      "F_at_day_0": 1.7685,
      "F_at_day_30": 0.6852,
      "F_at_day_100": 1.5811,
      "F_at_day_200": 2.3328,
      "reached_threshold": true
    },
    "identity": {
      "usable_lifetime_days": null,
      "F_at_day_0": 1.7685,
      "F_at_day_30": 1.6281,
      "F_at_day_100": 1.1161,
      "F_at_day_200": 0.3658,
      "reached_threshold": false
    }
  },
  "sampled_ages": [
    0,
    1,
    2,
    3,
    5,
    7,
    10,
    15,
    20,
    25,
    30,
    40,
    50,
    60,
    75,
    100,
    125,
    150,
    175,
    200
  ],
  "full_curves": {
    "tool_state": [
      {
        "age": 0,
        "F": 1.7685
      },
      {
        "age": 1,
        "F": 1.3231
      },
      {
        "age": 2,
        "F": 0.6852
      },
      {
        "age": 3,
        "F": 0.2901
      },
      {
        "age": 5,
        "F": 0.8702
      },
      {
        "age": 7,
        "F": 1.687
      },
      {
        "age": 10,
        "F": 2.1895
      },
      {
        "age": 15,
        "F": 2.3578
      },
      {
        "age": 20,
        "F": 2.3776
      },
      {
        "age": 25,
        "F": 2.3802
      },
      {
        "age": 30,
        "F": 2.3799
      },
      {
        "age": 40,
        "F": 2.3782
      },
      {
        "age": 50,
        "F": 2.3776
      },
      {
        "age": 60,
        "F": 2.3783
      },
      {
        "age": 75,
        "F": 2.3783
      },
      {
        "age": 100,
        "F": 2.3783
      },
      {
        "age": 125,
        "F": 2.3783
      },
      {
        "age": 150,
        "F": 2.3783
      },
      {
        "age": 175,
        "F": 2.3783
      },
      {
        "age": 200,
        "F": 2.3783
      }
    ],
    "episodic": [
      {
        "age": 0,
        "F": 1.7685
      },
      {
        "age": 1,
        "F": 1.6538
      },
      {
        "age": 2,
        "F": 1.5059
      },
      {
        "age": 3,
        "F": 1.3231
      },
      {
        "age": 5,
        "F": 0.8993
      },
      {
        "age": 7,
        "F": 0.5042
      },
      {
        "age": 10,
        "F": 0.2768
      },
      {
        "age": 15,
        "F": 0.8702
      },
      {
        "age": 20,
        "F": 1.5811
      },
      {
        "age": 25,
        "F": 1.9876
      },
      {
        "age": 30,
        "F": 2.1895
      },
      {
        "age": 40,
        "F": 2.3328
      },
      {
        "age": 50,
        "F": 2.3684
      },
      {
        "age": 60,
        "F": 2.3776
      },
      {
        "age": 75,
        "F": 2.3802
      },
      {
        "age": 100,
        "F": 2.3792
      },
      {
        "age": 125,
        "F": 2.3782
      },
      {
        "age": 150,
        "F": 2.3776
      },
      {
        "age": 175,
        "F": 2.3783
      },
      {
        "age": 200,
        "F": 2.3783
      }
    ],
    "semantic": [
      {
        "age": 0,
        "F": 1.7685
      },
      {
        "age": 1,
        "F": 1.7478
      },
      {
        "age": 2,
        "F": 1.7266
      },
      {
        "age": 3,
        "F": 1.7028
      },
      {
        "age": 5,
        "F": 1.6538
      },
      {
        "age": 7,
        "F": 1.598
      },
      {
        "age": 10,
        "F": 1.5059
      },
      {
        "age": 15,
        "F": 1.3231
      },
      {
        "age": 20,
        "F": 1.1161
      },
      {
        "age": 25,
        "F": 0.8993
      },
      {
        "age": 30,
        "F": 0.6852
      },
      {
        "age": 40,
        "F": 0.3658
      },
      {
        "age": 50,
        "F": 0.2768
      },
      {
        "age": 60,
        "F": 0.4199
      },
      {
        "age": 75,
        "F": 0.8702
      },
      {
        "age": 100,
        "F": 1.5811
      },
      {
        "age": 125,
        "F": 1.9876
      },
      {
        "age": 150,
        "F": 2.1895
      },
      {
        "age": 175,
        "F": 2.2845
      },
      {
        "age": 200,
        "F": 2.3328
      }
    ],
    "identity": [
      {
        "age": 0,
        "F": 1.7685
      },
      {
        "age": 1,
        "F": 1.7646
      },
      {
        "age": 2,
        "F": 1.7601
      },
      {
        "age": 3,
        "F": 1.7562
      },
      {
        "age": 5,
        "F": 1.7478
      },
      {
        "age": 7,
        "F": 1.7395
      },
      {
        "age": 10,
        "F": 1.7266
      },
      {
        "age": 15,
        "F": 1.7028
      },
      {
        "age": 20,
        "F": 1.6792
      },
      {
        "age": 25,
        "F": 1.6538
      },
      {
        "age": 30,
        "F": 1.6281
      },
      {
        "age": 40,
        "F": 1.5692
      },
      {
        "age": 50,
        "F": 1.5059
      },
      {
        "age": 60,
        "F": 1.4369
      },
      {
        "age": 75,
        "F": 1.3231
      },
      {
        "age": 100,
        "F": 1.1161
      },
      {
        "age": 125,
        "F": 0.8993
      },
      {
        "age": 150,
        "F": 0.6852
      },
      {
        "age": 175,
        "F": 0.5042
      },
      {
        "age": 200,
        "F": 0.3658
      }
    ]
  },
  "score_history_seed": [
    50,
    55,
    60,
    65,
    70,
    75,
    80,
    75,
    70,
    65
  ]
}